linearEquation/__init__.py
linearEquation/linearEquation.py
linearEquationSolver-1.2.dist-info/LICENSE
linearEquationSolver-1.2.dist-info/METADATA
linearEquationSolver-1.2.dist-info/WHEEL
linearEquationSolver-1.2.dist-info/top_level.txt
linearEquationSolver-1.2.dist-info/RECORD
