Metadata-Version: 2.1
Name: linearEquationSolver
Version: 1.2
Summary: Module to solve linear equations in 2 and 3 variables
Author: Sanjeevan Rames
Author-email: sanjeevanrames11@gmail.com
License: MIT
Keywords: python,linear Equation
License-File: LICENSE
